<?xml version="1.0" encoding="UTF-8"?>
<launch4jConfig>
  <dontWrapJar>false</dontWrapJar>
  <headerType>console</headerType>
  <jar>S:\projects\mhisoft\RdPro\target\RdPro-1.0.jar</jar>
  <outfile>S:\projects\mhisoft\RdPro\target\rdpro.exe</outfile>
  <errTitle></errTitle>
  <cmdLine></cmdLine>
  <chdir></chdir>
  <priority>normal</priority>
  <downloadUrl>http://java.com/download</downloadUrl>
  <supportUrl></supportUrl>
  <stayAlive>false</stayAlive>
  <manifest></manifest>
  <icon></icon>
  <jre>
    <path></path>
    <bundledJre64Bit>false</bundledJre64Bit>
    <minVersion>1.6.0</minVersion>
    <maxVersion></maxVersion>
    <jdkPreference>preferJre</jdkPreference>
    <runtimeBits>64/32</runtimeBits>
  </jre>
  <versionInfo>
    <fileVersion>0.9.0.1</fileVersion>
    <txtFileVersion>0.9</txtFileVersion>
    <fileDescription>Recursive Delete Pro</fileDescription>
    <copyright>Copyright(c) 2014Tony Xue</copyright>
    <productVersion>0.9.0.1</productVersion>
    <txtProductVersion>0.9</txtProductVersion>
    <productName>Recursive Delete Pro</productName>
    <companyName>MHISoft</companyName>
    <internalName>RdPro</internalName>
    <originalFilename>RdPro.exe</originalFilename>
  </versionInfo>
</launch4jConfig>